{
    "name" : "Amelia County", 
	"state" : "Virginia", 
	"FIPS" : "51007",
    "population" : 12793, 
    "demographics" : {
        "race_and_ethnicity" : {
            "White" : 0.72203549, 
            "Hispanic" : 0.0118815, 
            "Black" : 0.23528492, 
            "Asian" : 0.00125068, 
            "Mixed" : 0.02188697, 
            "Other" : 0.007660439999999999
        }, 
        "age_and_sex" : {
            "85+" : 0.02157, 
            "80-84" : 0.01321, 
            "75-79" : 0.0333, 
            "70-74" : 0.05229, 
            "67-69" : 0.02619, 
            "65-66" : 0.0351, 
            "62-64" : 0.04354, 
            "60-61" : 0.02603, 
            "55-59" : 0.08653000000000001, 
            "50-54" : 0.08903, 
            "45-49" : 0.06777, 
            "40-44" : 0.04643, 
            "35-39" : 0.06418, 
            "30-34" : 0.04917, 
            "25-29" : 0.043230000000000005, 
            "22-24" : 0.045419999999999995, 
            "21" : 0.00954, 
            "20" : 0.00985, 
            "18-19" : 0.025169999999999998, 
            "15-17" : 0.037360000000000004, 
            "10-14" : 0.053470000000000004, 
            "5-9" : 0.06676, 
            "0-4" : 0.05487
        }, 
        "household_types" : {
            "Married" : 0.6061674, 
            "Single Female" : 0.13986784, 
            "Single Male" : 0.0154185, 
            "One-Person" : 0.20088106, 
            "Other Non-Family" : 0.037665199999999996
        }, 
        "marital_status" : {
            "Never Married" : {
                "female" : 0.23036352999999998, 
                "male" : 0.28813883
            }, 
            "Now Married" : {
                "female" : 0.51553965, 
                "male" : 0.53794813
            }, 
            "Separated" : {
                "female" : 0.01280844, 
                "male" : 0.02383677
            }, 
            "Absent Spouse" : {
                "female" : 0.01619891, 
                "male" : 0.01792525
            }, 
            "Widowed" : {
                "female" : 0.13580712, 
                "male" : 0.024408850000000003
            }, 
            "Divorced" : {
                "female" : 0.08928235000000001, 
                "male" : 0.10774217999999999
            }
        }, 
        "ancestry" : {
            "Other" : 0.32345813999999995, 
            "Unclassified" : 0.19197999, 
            "English" : 0.13507386999999998, 
            "German" : 0.10646447, 
            "American" : 0.09583366, 
            "Irish" : 0.0940358, 
            "Italian" : 0.03775502, 
            "Scottish" : 0.024701010000000002, 
            "European" : 0.023215819999999998, 
            "Scotch-Irish" : 0.022746810000000003, 
            "Subsaharan African" : 0.01797858, 
            "African" : 0.01797858, 
            "Polish" : 0.01750958, 
            "Swiss" : 0.01664973, 
            "French" : 0.01438287, 
            "Dutch" : 0.01328852, 
            "Welsh" : 0.01070898, 
            "Pennsylvania German" : 0.006253419999999999, 
            "Arab" : 0.00601892, 
            "Lebanese" : 0.00601892, 
            "Mexican" : 0.8947368400000001, 
            "Other Hispanic" : 0.010629999999999999, 
            "Spanish" : 0.10526316, 
            "Filipino" : 1.0
        }, 
        "employment_status" : {
            "Armed Forces" : 0.0, 
            "Employed" : 0.57820179, 
            "Unemployed" : 0.02428448, 
            "Other" : 0.39751373
        }, 
        "industries" : {
            "Healthcare" : 0.15883333, 
            "Retail" : 0.13283333, 
            "Manufacturing" : 0.09383333, 
            "Government" : 0.08083333, 
            "Education" : 0.07733333, 
            "Construction" : 0.06366667, 
            "Finance & Insurance" : 0.061333330000000005, 
            "Other Services" : 0.058333329999999996, 
            "Hospitality" : 0.05366667, 
            "Professional" : 0.05216667, 
            "Agriculture" : 0.0405, 
            "Transportation" : 0.0345, 
            "Wholesalers" : 0.027999999999999997, 
            "Administrative" : 0.022166670000000003, 
            "Utilities" : 0.01466667, 
            "Entertainment" : 0.008166670000000001, 
            "Oil & Gas, and Mining" : 0.008, 
            "Real estate" : 0.00783333, 
            "Information" : 0.00333333, 
            "Management" : 0.0
        }, 
        "educational_attainment" : {
            "Doctorate" : 0.00302555, 
            "Professional" : 0.00874048, 
            "Master's" : 0.029807260000000002, 
            "Bachelor's" : 0.09917078, 
            "Associate's" : 0.061519500000000005, 
            "Some College" : 0.24204393, 
            "High School" : 0.36822053, 
            "Some H.S." : 0.10948005, 
            "Less than H.S." : 0.0417974, 
            "None" : 0.03619453
        }
    }
}