{
    "name" : "Jackson County", 
	"state" : "Georgia", 
	"FIPS" : "13157",
    "population" : 62131, 
    "demographics" : {
        "race_and_ethnicity" : {
            "White" : 0.82609325, 
            "Hispanic" : 0.06854871, 
            "Black" : 0.06977193, 
            "Asian" : 0.01804252, 
            "Mixed" : 0.014308479999999998, 
            "Other" : 0.0032351000000000003
        }, 
        "age_and_sex" : {
            "85+" : 0.00877, 
            "80-84" : 0.01252, 
            "75-79" : 0.02596, 
            "70-74" : 0.03905, 
            "67-69" : 0.0311, 
            "65-66" : 0.016819999999999998, 
            "62-64" : 0.03515, 
            "60-61" : 0.020390000000000002, 
            "55-59" : 0.06261, 
            "50-54" : 0.06984, 
            "45-49" : 0.07325999999999999, 
            "40-44" : 0.08348000000000001, 
            "35-39" : 0.06344999999999999, 
            "30-34" : 0.06333, 
            "25-29" : 0.05915, 
            "22-24" : 0.03132, 
            "21" : 0.011850000000000001, 
            "20" : 0.01188, 
            "18-19" : 0.02265, 
            "15-17" : 0.04249, 
            "10-14" : 0.07309, 
            "5-9" : 0.0761, 
            "0-4" : 0.06575
        }, 
        "household_types" : {
            "Married" : 0.5934170000000001, 
            "Single Female" : 0.11811508, 
            "Single Male" : 0.046601939999999994, 
            "One-Person" : 0.19507459000000002, 
            "Other Non-Family" : 0.04679138
        }, 
        "marital_status" : {
            "Never Married" : {
                "female" : 0.21719439000000001, 
                "male" : 0.26482562000000004
            }, 
            "Now Married" : {
                "female" : 0.51082164, 
                "male" : 0.55105553
            }, 
            "Separated" : {
                "female" : 0.02589178, 
                "male" : 0.022117770000000002
            }, 
            "Absent Spouse" : {
                "female" : 0.02264529, 
                "male" : 0.03458262
            }, 
            "Widowed" : {
                "female" : 0.09839679, 
                "male" : 0.02215973
            }, 
            "Divorced" : {
                "female" : 0.1250501, 
                "male" : 0.10525874
            }
        }, 
        "ancestry" : {
            "Other" : 0.35838791999999997, 
            "Unclassified" : 0.2022018, 
            "American" : 0.17931467, 
            "Irish" : 0.10154351, 
            "German" : 0.08995509, 
            "English" : 0.08427355, 
            "Scottish" : 0.02353093, 
            "Italian" : 0.02077868, 
            "Scotch-Irish" : 0.0181069, 
            "European" : 0.012489740000000001, 
            "French" : 0.011829840000000001, 
            "Dutch" : 0.00862693, 
            "Polish" : 0.00753247, 
            "Swedish" : 0.00569764, 
            "Mexican" : 0.56100949, 
            "Central American" : 0.039, 
            "Salvadoran" : 0.26232924, 
            "South American" : 0.01824, 
            "Puerto Rican" : 0.18916416000000003, 
            "Colombian" : 0.01315, 
            "Peruvian" : 0.07802732, 
            "Honduran" : 0.00542, 
            "Costa Rican" : 0.061356799999999996, 
            "Cuban" : 0.0042699999999999995, 
            "Nicaraguan" : 0.034498730000000005, 
            "Other Hispanic" : 0.0024, 
            "Argentinean" : 0.03056263, 
            "Guatemalan" : 0.00212, 
            "Venezuelan" : 0.02616346, 
            "Hmong" : 0.50401427, 
            "Korean" : 0.00909, 
            "Filipino" : 0.22747547, 
            "Mixed" : 0.0040999999999999995, 
            "Indian" : 0.06601249000000001, 
            "Not Specified" : 0.0011899999999999999, 
            "Japanese" : 0.05263158, 
            "Chinese" : 0.00095, 
            "Indonesian" : 0.049955400000000004, 
            "Vietnamese" : 0.0009
        }, 
        "employment_status" : {
            "Armed Forces" : 0.00137816, 
            "Employed" : 0.5615995, 
            "Unemployed" : 0.040780960000000005, 
            "Other" : 0.39624138999999997
        }, 
        "industries" : {
            "Manufacturing" : 0.15307678, 
            "Retail" : 0.14248001, 
            "Healthcare" : 0.11987358000000001, 
            "Education" : 0.09306563000000001, 
            "Construction" : 0.07425172, 
            "Hospitality" : 0.058709800000000006, 
            "Other Services" : 0.04740658, 
            "Wholesalers" : 0.04495259, 
            "Government" : 0.043465329999999996, 
            "Transportation" : 0.042535790000000004, 
            "Administrative" : 0.041048520000000005, 
            "Finance & Insurance" : 0.03978435, 
            "Professional" : 0.03840863, 
            "Information" : 0.01427775, 
            "Entertainment" : 0.01427775, 
            "Real estate" : 0.01141476, 
            "Agriculture" : 0.010559579999999999, 
            "Utilities" : 0.00884923, 
            "Oil & Gas, and Mining" : 0.00085518, 
            "Management" : 0.00070645
        }, 
        "educational_attainment" : {
            "Doctorate" : 0.00532559, 
            "Professional" : 0.01607359, 
            "Master's" : 0.04170903, 
            "Bachelor's" : 0.12757202, 
            "Associate's" : 0.07944808, 
            "Some College" : 0.21411281, 
            "High School" : 0.33297023000000003, 
            "Some H.S." : 0.1184459, 
            "Less than H.S." : 0.050568869999999995, 
            "None" : 0.013773899999999999
        }
    }
}