{
    "name" : "Stone County", 
	"state" : "Arkansas", 
	"FIPS" : "05137",
    "population" : 12503, 
    "demographics" : {
        "race_and_ethnicity" : {
            "White" : 0.95185156, 
            "Hispanic" : 0.01703591, 
            "Black" : 0.00079981, 
            "Asian" : 0.0020794999999999998, 
            "Mixed" : 0.02511397, 
            "Other" : 0.00311925
        }, 
        "age_and_sex" : {
            "85+" : 0.01872, 
            "80-84" : 0.036070000000000005, 
            "75-79" : 0.05255, 
            "70-74" : 0.06854, 
            "67-69" : 0.03487, 
            "65-66" : 0.04263, 
            "62-64" : 0.04551, 
            "60-61" : 0.03215, 
            "55-59" : 0.08038000000000001, 
            "50-54" : 0.0747, 
            "45-49" : 0.05631, 
            "40-44" : 0.04271, 
            "35-39" : 0.057830000000000006, 
            "30-34" : 0.04295, 
            "25-29" : 0.04543, 
            "22-24" : 0.026629999999999997, 
            "21" : 0.00688, 
            "20" : 0.01544, 
            "18-19" : 0.019039999999999998, 
            "15-17" : 0.036469999999999995, 
            "10-14" : 0.06079, 
            "5-9" : 0.05679, 
            "0-4" : 0.046630000000000005
        }, 
        "household_types" : {
            "Married" : 0.5432944, 
            "Single Female" : 0.07410391, 
            "Single Male" : 0.03624648, 
            "One-Person" : 0.3123238, 
            "Other Non-Family" : 0.034031410000000005
        }, 
        "marital_status" : {
            "Never Married" : {
                "female" : 0.14692308, 
                "male" : 0.21809524
            }, 
            "Now Married" : {
                "female" : 0.49576923, 
                "male" : 0.5758095200000001
            }, 
            "Separated" : {
                "female" : 0.02288462, 
                "male" : 0.01390476
            }, 
            "Absent Spouse" : {
                "female" : 0.03288462, 
                "male" : 0.02761905
            }, 
            "Widowed" : {
                "female" : 0.15326923, 
                "male" : 0.03657143
            }, 
            "Divorced" : {
                "female" : 0.14826923, 
                "male" : 0.128
            }
        }, 
        "ancestry" : {
            "Unclassified" : 0.24130209, 
            "Other" : 0.21154923, 
            "American" : 0.18259618, 
            "English" : 0.15356314, 
            "Irish" : 0.14820443, 
            "German" : 0.08509958, 
            "Scottish" : 0.03615132, 
            "French" : 0.03519155, 
            "Scotch-Irish" : 0.02735344, 
            "European" : 0.02183476, 
            "Dutch" : 0.01047749, 
            "Italian" : 0.0079181, 
            "Polish" : 0.0058386, 
            "Swedish" : 0.0058386, 
            "Norwegian" : 0.005198749999999999, 
            "Mexican" : 0.61032864, 
            "Other Hispanic" : 0.0104, 
            "Spanish" : 0.23943662, 
            "Puerto Rican" : 0.004079999999999999, 
            "Cuban" : 0.17840376, 
            "Spaniard" : 0.0030399999999999997, 
            "Vietnamese" : 1.0
        }, 
        "employment_status" : {
            "Armed Forces" : 0.0, 
            "Employed" : 0.42369751, 
            "Unemployed" : 0.03713064, 
            "Other" : 0.53917185
        }, 
        "industries" : {
            "Education" : 0.1364992, 
            "Healthcare" : 0.11860518, 
            "Agriculture" : 0.10323468999999999, 
            "Construction" : 0.10323468999999999, 
            "Retail" : 0.09956412, 
            "Hospitality" : 0.09474650000000001, 
            "Manufacturing" : 0.06974077000000001, 
            "Other Services" : 0.04519385, 
            "Government" : 0.03693508, 
            "Oil & Gas, and Mining" : 0.035788020000000004, 
            "Transportation" : 0.02982335, 
            "Wholesalers" : 0.02890571, 
            "Professional" : 0.02592338, 
            "Real estate" : 0.01605873, 
            "Administrative" : 0.014682269999999999, 
            "Entertainment" : 0.013305800000000001, 
            "Utilities" : 0.01261757, 
            "Finance & Insurance" : 0.01147052, 
            "Information" : 0.00367057, 
            "Management" : 0.0
        }, 
        "educational_attainment" : {
            "Doctorate" : 0.0, 
            "Professional" : 0.021762899999999998, 
            "Master's" : 0.04319773, 
            "Bachelor's" : 0.07950569, 
            "Associate's" : 0.07283465, 
            "Some College" : 0.19750656, 
            "High School" : 0.35050306, 
            "Some H.S." : 0.13101487, 
            "Less than H.S." : 0.06572616, 
            "None" : 0.03794838
        }
    }
}