{
    "name" : "East Carroll Parish", 
	"state" : "Louisiana", 
	"FIPS" : "22035",
    "population" : 7419, 
    "demographics" : {
        "race_and_ethnicity" : {
            "White" : 0.26688233, 
            "Hispanic" : 0.00781777, 
            "Black" : 0.71128184, 
            "Asian" : 0.0, 
            "Mixed" : 0.01401806, 
            "Other" : 0.0
        }, 
        "age_and_sex" : {
            "85+" : 0.01698, 
            "80-84" : 0.0128, 
            "75-79" : 0.021429999999999998, 
            "70-74" : 0.04138, 
            "67-69" : 0.01591, 
            "65-66" : 0.02022, 
            "62-64" : 0.023319999999999997, 
            "60-61" : 0.02521, 
            "55-59" : 0.07696, 
            "50-54" : 0.058230000000000004, 
            "45-49" : 0.055940000000000004, 
            "40-44" : 0.0434, 
            "35-39" : 0.05769, 
            "30-34" : 0.06322, 
            "25-29" : 0.08694, 
            "22-24" : 0.09004, 
            "21" : 0.0217, 
            "20" : 0.00768, 
            "18-19" : 0.02237, 
            "15-17" : 0.0403, 
            "10-14" : 0.07306, 
            "5-9" : 0.08667, 
            "0-4" : 0.03855
        }, 
        "household_types" : {
            "Married" : 0.26828314, 
            "Single Female" : 0.29605006, 
            "Single Male" : 0.04419241, 
            "One-Person" : 0.36800939, 
            "Other Non-Family" : 0.023465
        }, 
        "marital_status" : {
            "Never Married" : {
                "female" : 0.40925409, 
                "male" : 0.59314153
            }, 
            "Now Married" : {
                "female" : 0.28879138, 
                "male" : 0.1894798
            }, 
            "Separated" : {
                "female" : 0.0259274, 
                "male" : 0.02935193
            }, 
            "Absent Spouse" : {
                "female" : 0.017151970000000002, 
                "male" : 0.02789887
            }, 
            "Widowed" : {
                "female" : 0.14359792999999998, 
                "male" : 0.04533566000000001
            }, 
            "Divorced" : {
                "female" : 0.11527722000000001, 
                "male" : 0.11479221
            }
        }, 
        "employment_status" : {
            "Armed Forces" : 0.0, 
            "Employed" : 0.3147832, 
            "Unemployed" : 0.040969610000000004, 
            "Other" : 0.64424718
        }, 
        "industries" : {
            "Healthcare" : 0.28741866, 
            "Retail" : 0.12527115, 
            "Agriculture" : 0.10357917999999999, 
            "Education" : 0.09598698, 
            "Other Services" : 0.06778742, 
            "Manufacturing" : 0.06127983000000001, 
            "Government" : 0.04989154, 
            "Finance & Insurance" : 0.04880694, 
            "Construction" : 0.04501085, 
            "Hospitality" : 0.039045550000000005, 
            "Transportation" : 0.02169197, 
            "Wholesalers" : 0.01572668, 
            "Real estate" : 0.01138829, 
            "Oil & Gas, and Mining" : 0.00976139, 
            "Information" : 0.00433839, 
            "Administrative" : 0.00433839, 
            "Entertainment" : 0.00433839, 
            "Professional" : 0.0037961, 
            "Utilities" : 0.0005423, 
            "Management" : 0.0
        }, 
        "educational_attainment" : {
            "Doctorate" : 0.00630846, 
            "Professional" : 0.0019578, 
            "Master's" : 0.016750050000000002, 
            "Bachelor's" : 0.08766586999999999, 
            "Associate's" : 0.03502284, 
            "Some College" : 0.19099412999999998, 
            "High School" : 0.36567327, 
            "Some H.S." : 0.21905591000000002, 
            "Less than H.S." : 0.055906029999999995, 
            "None" : 0.02066565
        }
    }
}