{
    "name" : "Fayette County", 
	"state" : "Ohio", 
	"FIPS" : "39047",
    "population" : 28719, 
    "demographics" : {
        "race_and_ethnicity" : {
            "White" : 0.9314043, 
            "Hispanic" : 0.01876806, 
            "Black" : 0.01967339, 
            "Asian" : 0.00752115, 
            "Mixed" : 0.02169296, 
            "Other" : 0.00094014
        }, 
        "age_and_sex" : {
            "85+" : 0.01724, 
            "80-84" : 0.021030000000000004, 
            "75-79" : 0.03071, 
            "70-74" : 0.04074, 
            "67-69" : 0.03061, 
            "65-66" : 0.02472, 
            "62-64" : 0.03781, 
            "60-61" : 0.025840000000000002, 
            "55-59" : 0.07417, 
            "50-54" : 0.07016, 
            "45-49" : 0.07163, 
            "40-44" : 0.07203999999999999, 
            "35-39" : 0.05383, 
            "30-34" : 0.05731, 
            "25-29" : 0.05808, 
            "22-24" : 0.03576, 
            "21" : 0.00916, 
            "20" : 0.01027, 
            "18-19" : 0.02009, 
            "15-17" : 0.04199, 
            "10-14" : 0.05428, 
            "5-9" : 0.07883, 
            "0-4" : 0.06369
        }, 
        "household_types" : {
            "Married" : 0.48139894, 
            "Single Female" : 0.13886508, 
            "Single Male" : 0.051260070000000005, 
            "One-Person" : 0.27438711, 
            "Other Non-Family" : 0.05408881
        }, 
        "marital_status" : {
            "Never Married" : {
                "female" : 0.20737753, 
                "male" : 0.27091170000000003
            }, 
            "Now Married" : {
                "female" : 0.48962272, 
                "male" : 0.5129858500000001
            }, 
            "Separated" : {
                "female" : 0.0310058, 
                "male" : 0.02901666
            }, 
            "Absent Spouse" : {
                "female" : 0.01092345, 
                "male" : 0.014239660000000001
            }, 
            "Widowed" : {
                "female" : 0.09108478, 
                "male" : 0.02641949
            }, 
            "Divorced" : {
                "female" : 0.16998572, 
                "male" : 0.14642665
            }
        }, 
        "ancestry" : {
            "Other" : 0.34928096, 
            "Unclassified" : 0.23806539000000002, 
            "American" : 0.14561788, 
            "German" : 0.13715659, 
            "Irish" : 0.08785125, 
            "English" : 0.07803196, 
            "Dutch" : 0.0172708, 
            "French" : 0.01570389, 
            "Scottish" : 0.01333612, 
            "Italian" : 0.01142101, 
            "European" : 0.00804346, 
            "Scotch-Irish" : 0.006581010000000001, 
            "Mexican" : 0.8571428600000001, 
            "Other Hispanic" : 0.01609, 
            "Puerto Rican" : 0.10018553000000001, 
            "Spaniard" : 0.00188, 
            "Indian" : 0.7037036999999999, 
            "Korean" : 0.00529, 
            "Japanese" : 0.25
        }, 
        "employment_status" : {
            "Armed Forces" : 0.00128013, 
            "Employed" : 0.55001324, 
            "Unemployed" : 0.040787500000000004, 
            "Other" : 0.40791913
        }, 
        "industries" : {
            "Manufacturing" : 0.19149278, 
            "Retail" : 0.16340289, 
            "Healthcare" : 0.14470305, 
            "Education" : 0.06669342, 
            "Construction" : 0.06083467, 
            "Hospitality" : 0.055296950000000004, 
            "Government" : 0.055296950000000004, 
            "Transportation" : 0.05256822, 
            "Other Services" : 0.044061, 
            "Agriculture" : 0.042536120000000004, 
            "Wholesalers" : 0.02985554, 
            "Administrative" : 0.02520064, 
            "Finance & Insurance" : 0.01990369, 
            "Professional" : 0.01829856, 
            "Real estate" : 0.01107544, 
            "Information" : 0.01027287, 
            "Entertainment" : 0.00457464, 
            "Utilities" : 0.0024077, 
            "Oil & Gas, and Mining" : 0.00080257, 
            "Management" : 0.00072231
        }, 
        "educational_attainment" : {
            "Doctorate" : 0.00233514, 
            "Professional" : 0.0045179999999999994, 
            "Master's" : 0.02660034, 
            "Bachelor's" : 0.11163002999999999, 
            "Associate's" : 0.0748769, 
            "Some College" : 0.15985583, 
            "High School" : 0.49413676, 
            "Some H.S." : 0.09959896, 
            "Less than H.S." : 0.01923956, 
            "None" : 0.00720849
        }
    }
}